tensorchat_streaming/__init__.py
tensorchat_streaming/client.py
tensorchat_streaming/manager.py
tensorchat_streaming/types.py
tensorchat_streaming-1.0.5.dist-info/licenses/LICENSE
tensorchat_streaming-1.0.5.dist-info/METADATA
tensorchat_streaming-1.0.5.dist-info/WHEEL
tensorchat_streaming-1.0.5.dist-info/top_level.txt
tensorchat_streaming-1.0.5.dist-info/RECORD
