Metadata-Version: 2.4
Name: tensorchat-streaming
Version: 1.0.5
Summary: Framework-agnostic Python client for Tensorchat.io streaming API
Home-page: https://github.com/datacorridor/tensorchat-streaming
Author: Tensorchat.io
Author-email: "Tensorchat.io" <support@tensorchat.io>
License-Expression: MIT
Project-URL: Homepage, https://tensorchat.io
Project-URL: Documentation, https://tensorchat.io/docs
Project-URL: Repository, https://github.com/datacorridor/tensorchat-streaming
Project-URL: Bug Tracker, https://github.com/datacorridor/tensorchat-streaming/issues
Keywords: tensorchat,streaming,ai,real-time,llm,async,python,openrouter,concurrent
Classifier: Development Status :: 4 - Beta
Classifier: Intended Audience :: Developers
Classifier: Topic :: Software Development :: Libraries :: Python Modules
Classifier: Topic :: Scientific/Engineering :: Artificial Intelligence
Classifier: Programming Language :: Python :: 3
Classifier: Programming Language :: Python :: 3.8
Classifier: Programming Language :: Python :: 3.9
Classifier: Programming Language :: Python :: 3.10
Classifier: Programming Language :: Python :: 3.11
Classifier: Programming Language :: Python :: 3.12
Classifier: Operating System :: OS Independent
Classifier: Framework :: AsyncIO
Requires-Python: >=3.8
License-File: LICENSE
Requires-Dist: aiohttp>=3.8.0
Provides-Extra: dev
Requires-Dist: pytest>=7.0.0; extra == "dev"
Requires-Dist: pytest-asyncio>=0.21.0; extra == "dev"
Requires-Dist: black>=22.0.0; extra == "dev"
Requires-Dist: flake8>=4.0.0; extra == "dev"
Requires-Dist: mypy>=0.950; extra == "dev"
Requires-Dist: pre-commit>=2.20.0; extra == "dev"
Provides-Extra: test
Requires-Dist: pytest>=7.0.0; extra == "test"
Requires-Dist: pytest-asyncio>=0.21.0; extra == "test"
Requires-Dist: pytest-cov>=4.0.0; extra == "test"
Dynamic: author
Dynamic: home-page
Dynamic: license-file
Dynamic: requires-python
